[{
  "_id": {
    "$binary": {
      "base64": "4GHNTwWECh8M1Saj1U/ouw==",
      "subType": "03"
    }
  },
  "business": {
    "_id": {
      "$binary": {
        "base64": "img60ibL7R4pstoZnVdjvQ==",
        "subType": "03"
      }
    },
    "name": "Simpo.ai"
  },
  "project": {
    "_id": {
      "$binary": {
        "base64": "gEhAby2IUhRLhfLyr3iclA==",
        "subType": "03"
      }
    },
    "name": "Simpo Tech"
  },
  "workItemId": {
    "$binary": {
      "base64": "FEkcfzuacVwVJ1nU5sANmQ==",
      "subType": "03"
    }
  },
  "workItemTitle": "Backend Learning Session",
  "type": "STATE_CHANGED",
  "user": {
    "_id": {
      "$binary": {
        "base64": "ZWPtXFdoBx+nRFXdzzU0tQ==",
        "subType": "03"
      }
    },
    "name": "Manish Chhabra"
  },
  "fieldChanged": "State",
  "message": " changed state from In-Progress to Done.",
  "oldValue": "In-Progress",
  "newValue": "Done",
  "timestamp": {
    "$date": "2025-10-13T14:24:30.571Z"
  },
  "_class": "com.lm.project.project_management.pms.model.timeline.Timeline"
},
{
  "_id": {
    "$binary": {
      "base64": "JWRtHAWECh/+7gIzJnHouw==",
      "subType": "03"
    }
  },
  "business": {
    "_id": {
      "$binary": {
        "base64": "img60ibL7R4pstoZnVdjvQ==",
        "subType": "03"
      }
    },
    "name": "Simpo.ai"
  },
  "project": {
    "_id": {
      "$binary": {
        "base64": "gEhAby2IUhRLhfLyr3iclA==",
        "subType": "03"
      }
    },
    "name": "Simpo Tech"
  },
  "workItemId": {
    "$binary": {
      "base64": "/kX2CqN2Su4bM256EW2MsQ==",
      "subType": "03"
    }
  },
  "workItemTitle": "Documents - Add Document Button Validation in Edit Document ",
  "type": "STATE_CHANGED",
  "user": {
    "_id": {
      "$binary": {
        "base64": "ZWPtXFdoBx+nRFXdzzU0tQ==",
        "subType": "03"
      }
    },
    "name": "Manish Chhabra"
  },
  "fieldChanged": "State",
  "message": " changed state from Todo to Done.",
  "oldValue": "Todo",
  "newValue": "Done",
  "timestamp": {
    "$date": "2025-10-13T14:24:25.184Z"
  },
  "_class": "com.lm.project.project_management.pms.model.timeline.Timeline"
},
{
  "_id": {
    "$binary": {
      "base64": "yGBa8wSECh8I0z8c9mXouw==",
      "subType": "03"
    }
  },
  "business": {
    "_id": {
      "$binary": {
        "base64": "img60ibL7R4pstoZnVdjvQ==",
        "subType": "03"
      }
    },
    "name": "Simpo.ai"
  },
  "project": {
    "_id": {
      "$binary": {
        "base64": "gEhAby2IUhRLhfLyr3iclA==",
        "subType": "03"
      }
    },
    "name": "Simpo Tech"
  },
  "workItemId": {
    "$binary": {
      "base64": "/kX2CqN2Su4bM256EW2MsQ==",
      "subType": "03"
    }
  },
  "workItemTitle": "Documents - Add Document Button Validation in Edit Document ",
  "type": "TIME_LOGGED",
  "user": {
    "_id": {
      "$binary": {
        "base64": "ZWPtXFdoBx+nRFXdzzU0tQ==",
        "subType": "03"
      }
    },
    "name": "Manish Chhabra"
  },
  "commentText": "issue is resolved",
  "fieldChanged": "workLogs",
  "message": " logged 30 min",
  "newValue": "30 min",
  "timestamp": {
    "$date": "2025-10-13T14:24:20.877Z"
  },
  "_class": "com.lm.project.project_management.pms.model.timeline.Timeline"
},
{
  "_id": {
    "$binary": {
      "base64": "mGXlRASECh/aAkfjgUXouw==",
      "subType": "03"
    }
  },
  "business": {
    "_id": {
      "$binary": {
        "base64": "img60ibL7R4pstoZnVdjvQ==",
        "subType": "03"
      }
    },
    "name": "Simpo.ai"
  },
  "project": {
    "_id": {
      "$binary": {
        "base64": "gEhAby2IUhRLhfLyr3iclA==",
        "subType": "03"
      }
    },
    "name": "Simpo Tech"
  },
  "workItemId": {
    "$binary": {
      "base64": "/kX2CqN2Su4bM256EW2MsQ==",
      "subType": "03"
    }
  },
  "workItemTitle": "Documents - Add Document Button Validation in Edit Document ",
  "type": "UPDATED",
  "user": {
    "_id": {
      "$binary": {
        "base64": "ZWPtXFdoBx+nRFXdzzU0tQ==",
        "subType": "03"
      }
    },
    "name": "Manish Chhabra"
  },
  "message": " updated the work item details.",
  "timestamp": {
    "$date": "2025-10-13T14:24:02.584Z"
  },
  "_class": "com.lm.project.project_management.pms.model.timeline.Timeline"
},
{
  "_id": {
    "$binary": {
      "base64": "92o3cuaDCh9XfNeFQUXouw==",
      "subType": "03"
    }
  },
  "business": {
    "_id": {
      "$binary": {
        "base64": "img60ibL7R4pstoZnVdjvQ==",
        "subType": "03"
      }
    },
    "name": "Simpo.ai"
  },
  "project": {
    "_id": {
      "$binary": {
        "base64": "gEhAby2IUhRLhfLyr3iclA==",
        "subType": "03"
      }
    },
    "name": "Simpo Tech"
  },
  "workItemId": {
    "$binary": {
      "base64": "qUw6qguQgX+Fs3rvNngTiQ==",
      "subType": "03"
    }
  },
  "workItemTitle": "Null Check Issue While Creating Template",
  "type": "TIME_LOGGED",
  "user": {
    "_id": {
      "$binary": {
        "base64": "qWgg1ryqBx+oLnNj2numnw==",
        "subType": "03"
      }
    },
    "name": "Akhil"
  },
  "commentText": "Done",
  "fieldChanged": "workLogs",
  "message": " logged 15 min",
  "newValue": "15 min",
  "timestamp": {
    "$date": "2025-10-13T14:10:42.030Z"
  },
  "_class": "com.lm.project.project_management.pms.model.timeline.Timeline"
},
{
  "_id": {
    "$binary": {
      "base64": "jGED/uWDCh9J3n3J1OPouw==",
      "subType": "03"
    }
  },
  "business": {
    "_id": {
      "$binary": {
        "base64": "img60ibL7R4pstoZnVdjvQ==",
        "subType": "03"
      }
    },
    "name": "Simpo.ai"
  },
  "project": {
    "_id": {
      "$binary": {
        "base64": "gEhAby2IUhRLhfLyr3iclA==",
        "subType": "03"
      }
    },
    "name": "Simpo Tech"
  },
  "workItemId": {
    "$binary": {
      "base64": "qUw6qguQgX+Fs3rvNngTiQ==",
      "subType": "03"
    }
  },
  "workItemTitle": "Null Check Issue While Creating Template",
  "type": "CREATED",
  "user": {
    "_id": {
      "$binary": {
        "base64": "qWgg1ryqBx+oLnNj2numnw==",
        "subType": "03"
      }
    },
    "name": "Akhil"
  },
  "message": " created the work item.",
  "timestamp": {
    "$date": "2025-10-13T14:10:29.845Z"
  },
  "_class": "com.lm.project.project_management.pms.model.timeline.Timeline"
},
{
  "_id": {
    "$binary": {
      "base64": "ImicIOSDCh+/Mokz9Jnouw==",
      "subType": "03"
    }
  },
  "business": {
    "_id": {
      "$binary": {
        "base64": "img60ibL7R4pstoZnVdjvQ==",
        "subType": "03"
      }
    },
    "name": "Simpo.ai"
  },
  "project": {
    "_id": {
      "$binary": {
        "base64": "gEhAby2IUhRLhfLyr3iclA==",
        "subType": "03"
      }
    },
    "name": "Simpo Tech"
  },
  "workItemId": {
    "$binary": {
      "base64": "wEwQEbdW8ZbtNr59XwVgmg==",
      "subType": "03"
    }
  },
  "workItemTitle": "Back Redirection Issue In Templates",
  "type": "STATE_CHANGED",
  "user": {
    "_id": {
      "$binary": {
        "base64": "qWgg1ryqBx+oLnNj2numnw==",
        "subType": "03"
      }
    },
    "name": "Akhil"
  },
  "fieldChanged": "State",
  "message": " changed state from Todo to In-Progress.",
  "oldValue": "Todo",
  "newValue": "In-Progress",
  "timestamp": {
    "$date": "2025-10-13T14:09:39.786Z"
  },
  "_class": "com.lm.project.project_management.pms.model.timeline.Timeline"
},
{
  "_id": {
    "$binary": {
      "base64": "JGfv9uODCh9zZN4da9Pouw==",
      "subType": "03"
    }
  },
  "business": {
    "_id": {
      "$binary": {
        "base64": "img60ibL7R4pstoZnVdjvQ==",
        "subType": "03"
      }
    },
    "name": "Simpo.ai"
  },
  "project": {
    "_id": {
      "$binary": {
        "base64": "gEhAby2IUhRLhfLyr3iclA==",
        "subType": "03"
      }
    },
    "name": "Simpo Tech"
  },
  "workItemId": {
    "$binary": {
      "base64": "wEwQEbdW8ZbtNr59XwVgmg==",
      "subType": "03"
    }
  },
  "workItemTitle": "Back Redirection Issue In Templates",
  "type": "TIME_LOGGED",
  "user": {
    "_id": {
      "$binary": {
        "base64": "qWgg1ryqBx+oLnNj2numnw==",
        "subType": "03"
      }
    },
    "name": "Akhil"
  },
  "commentText": "Still Pending",
  "fieldChanged": "workLogs",
  "message": " logged 1 hr",
  "newValue": "1 hr",
  "timestamp": {
    "$date": "2025-10-13T14:09:35.416Z"
  },
  "_class": "com.lm.project.project_management.pms.model.timeline.Timeline"
},
{
  "_id": {
    "$binary": {
      "base64": "HW8iyuKDCh/uZjCmjLPouw==",
      "subType": "03"
    }
  },
  "business": {
    "_id": {
      "$binary": {
        "base64": "img60ibL7R4pstoZnVdjvQ==",
        "subType": "03"
      }
    },
    "name": "Simpo.ai"
  },
  "project": {
    "_id": {
      "$binary": {
        "base64": "gEhAby2IUhRLhfLyr3iclA==",
        "subType": "03"
      }
    },
    "name": "Simpo Tech"
  },
  "workItemId": {
    "$binary": {
      "base64": "2kuIsBsxJHxovXsLJXWjmw==",
      "subType": "03"
    }
  },
  "workItemTitle": "Editor Migration From Simpo Website Builder to Simpo Studio ",
  "type": "TIME_LOGGED",
  "user": {
    "_id": {
      "$binary": {
        "base64": "qWgg1ryqBx+oLnNj2numnw==",
        "subType": "03"
      }
    },
    "name": "Akhil"
  },
  "commentText": "Done",
  "fieldChanged": "workLogs",
  "message": " logged 43 min",
  "newValue": "43 min",
  "timestamp": {
    "$date": "2025-10-13T14:09:03.875Z"
  },
  "_class": "com.lm.project.project_management.pms.model.timeline.Timeline"
},
{
  "_id": {
    "$binary": {
      "base64": "B2AcHOKDCh9ALeUL/Bvouw==",
      "subType": "03"
    }
  },
  "business": {
    "_id": {
      "$binary": {
        "base64": "img60ibL7R4pstoZnVdjvQ==",
        "subType": "03"
      }
    },
    "name": "Simpo.ai"
  },
  "project": {
    "_id": {
      "$binary": {
        "base64": "gEhAby2IUhRLhfLyr3iclA==",
        "subType": "03"
      }
    },
    "name": "Simpo Tech"
  },
  "workItemId": {
    "$binary": {
      "base64": "okuTqn9hLZa8BfPbJXklsw==",
      "subType": "03"
    }
  },
  "workItemTitle": "Create Page from the template",
  "type": "TIME_LOGGED",
  "user": {
    "_id": {
      "$binary": {
        "base64": "qWgg1ryqBx+oLnNj2numnw==",
        "subType": "03"
      }
    },
    "name": "Akhil"
  },
  "commentText": "Done",
  "fieldChanged": "workLogs",
  "message": " logged 45 min",
  "newValue": "45 min",
  "timestamp": {
    "$date": "2025-10-13T14:08:45.626Z"
  },
  "_class": "com.lm.project.project_management.pms.model.timeline.Timeline"
},
{
  "_id": {
    "$binary": {
      "base64": "/GwUQ+GDCh9fLwe4JC3ouw==",
      "subType": "03"
    }
  },
  "business": {
    "_id": {
      "$binary": {
        "base64": "img60ibL7R4pstoZnVdjvQ==",
        "subType": "03"
      }
    },
    "name": "Simpo.ai"
  },
  "project": {
    "_id": {
      "$binary": {
        "base64": "gEhAby2IUhRLhfLyr3iclA==",
        "subType": "03"
      }
    },
    "name": "Simpo Tech"
  },
  "workItemId": {
    "$binary": {
      "base64": "ikzGVOwyG2WEMkq1b3k6iA==",
      "subType": "03"
    }
  },
  "workItemTitle": "Redeploy Simpo Admin",
  "type": "TIME_LOGGED",
  "user": {
    "_id": {
      "$binary": {
        "base64": "qWgg1ryqBx+oLnNj2numnw==",
        "subType": "03"
      }
    },
    "name": "Akhil"
  },
  "commentText": "Deployed 3 times",
  "fieldChanged": "workLogs",
  "message": " logged 2 hr",
  "newValue": "2 hr",
  "timestamp": {
    "$date": "2025-10-13T14:08:22.869Z"
  },
  "_class": "com.lm.project.project_management.pms.model.timeline.Timeline"
},
{
  "_id": {
    "$binary": {
      "base64": "cGLMD+CDCh9Ftwx1Ay3ouw==",
      "subType": "03"
    }
  },
  "business": {
    "_id": {
      "$binary": {
        "base64": "img60ibL7R4pstoZnVdjvQ==",
        "subType": "03"
      }
    },
    "name": "Simpo.ai"
  },
  "project": {
    "_id": {
      "$binary": {
        "base64": "gEhAby2IUhRLhfLyr3iclA==",
        "subType": "03"
      }
    },
    "name": "Simpo Tech"
  },
  "workItemId": {
    "$binary": {
      "base64": "90sBVDfmm5fhi2mqX8NCrw==",
      "subType": "03"
    }
  },
  "workItemTitle": "Should Give Hide Option for side bar in template creation",
  "type": "TIME_LOGGED",
  "user": {
    "_id": {
      "$binary": {
        "base64": "qWgg1ryqBx+oLnNj2numnw==",
        "subType": "03"
      }
    },
    "name": "Akhil"
  },
  "commentText": "Done",
  "fieldChanged": "workLogs",
  "message": " logged 20 min",
  "newValue": "20 min",
  "timestamp": {
    "$date": "2025-10-13T14:07:50.648Z"
  },
  "_class": "com.lm.project.project_management.pms.model.timeline.Timeline"
},
{
  "_id": {
    "$binary": {
      "base64": "Z2Rmlt6DCh9gKetAsTPouw==",
      "subType": "03"
    }
  },
  "business": {
    "_id": {
      "$binary": {
        "base64": "img60ibL7R4pstoZnVdjvQ==",
        "subType": "03"
      }
    },
    "name": "Simpo.ai"
  },
  "project": {
    "_id": {
      "$binary": {
        "base64": "gEhAby2IUhRLhfLyr3iclA==",
        "subType": "03"
      }
    },
    "name": "Simpo Tech"
  },
  "workItemId": {
    "$binary": {
      "base64": "HUIs2S9PZCf2DDwVw8hWtg==",
      "subType": "03"
    }
  },
  "workItemTitle": "Simpo Studio Template Lag",
  "type": "TIME_LOGGED",
  "user": {
    "_id": {
      "$binary": {
        "base64": "qWgg1ryqBx+oLnNj2numnw==",
        "subType": "03"
      }
    },
    "name": "Akhil"
  },
  "commentText": "Done",
  "fieldChanged": "workLogs",
  "message": " logged 29 min",
  "newValue": "29 min",
  "timestamp": {
    "$date": "2025-10-13T14:07:11.075Z"
  },
  "_class": "com.lm.project.project_management.pms.model.timeline.Timeline"
},
{
  "_id": {
    "$binary": {
      "base64": "WWTsyt2DCh+WAqwpxL3ouw==",
      "subType": "03"
    }
  },
  "business": {
    "_id": {
      "$binary": {
        "base64": "img60ibL7R4pstoZnVdjvQ==",
        "subType": "03"
      }
    },
    "name": "Simpo.ai"
  },
  "project": {
    "_id": {
      "$binary": {
        "base64": "gEhAby2IUhRLhfLyr3iclA==",
        "subType": "03"
      }
    },
    "name": "Simpo Tech"
  },
  "workItemId": {
    "$binary": {
      "base64": "hU41P1zC6UJhPM960Ahcig==",
      "subType": "03"
    }
  },
  "workItemTitle": "Deleting Button is not working Simpo Studio Editor",
  "type": "TIME_LOGGED",
  "user": {
    "_id": {
      "$binary": {
        "base64": "qWgg1ryqBx+oLnNj2numnw==",
        "subType": "03"
      }
    },
    "name": "Akhil"
  },
  "commentText": "Done",
  "fieldChanged": "workLogs",
  "message": " logged 30 min",
  "newValue": "30 min",
  "timestamp": {
    "$date": "2025-10-13T14:06:49.739Z"
  },
  "_class": "com.lm.project.project_management.pms.model.timeline.Timeline"
},
{
  "_id": {
    "$binary": {
      "base64": "ZWYTMd2DCh8fex7kJj/ouw==",
      "subType": "03"
    }
  },
  "business": {
    "_id": {
      "$binary": {
        "base64": "img60ibL7R4pstoZnVdjvQ==",
        "subType": "03"
      }
    },
    "name": "Simpo.ai"
  },
  "project": {
    "_id": {
      "$binary": {
        "base64": "gEhAby2IUhRLhfLyr3iclA==",
        "subType": "03"
      }
    },
    "name": "Simpo Tech"
  },
  "workItemId": {
    "$binary": {
      "base64": "vkdZSBaCKdr2Y0LY1kLPoA==",
      "subType": "03"
    }
  },
  "workItemTitle": "Unable to Select Divider in Simpo Studio Editor",
  "type": "TIME_LOGGED",
  "user": {
    "_id": {
      "$binary": {
        "base64": "qWgg1ryqBx+oLnNj2numnw==",
        "subType": "03"
      }
    },
    "name": "Akhil"
  },
  "commentText": "Done",
  "fieldChanged": "workLogs",
  "message": " logged 30 min",
  "newValue": "30 min",
  "timestamp": {
    "$date": "2025-10-13T14:06:33.607Z"
  },
  "_class": "com.lm.project.project_management.pms.model.timeline.Timeline"
},
{
  "_id": {
    "$binary": {
      "base64": "0WHIpdyDCh87UZ17e4/ouw==",
      "subType": "03"
    }
  },
  "business": {
    "_id": {
      "$binary": {
        "base64": "img60ibL7R4pstoZnVdjvQ==",
        "subType": "03"
      }
    },
    "name": "Simpo.ai"
  },
  "project": {
    "_id": {
      "$binary": {
        "base64": "gEhAby2IUhRLhfLyr3iclA==",
        "subType": "03"
      }
    },
    "name": "Simpo Tech"
  },
  "workItemId": {
    "$binary": {
      "base64": "1UY2F2ZzsWKbxTjkQU/0ig==",
      "subType": "03"
    }
  },
  "workItemTitle": "Pricing Section Add new and Delete item Functionality is not working in Studio",
  "type": "TIME_LOGGED",
  "user": {
    "_id": {
      "$binary": {
        "base64": "qWgg1ryqBx+oLnNj2numnw==",
        "subType": "03"
      }
    },
    "name": "Akhil"
  },
  "commentText": "Done",
  "fieldChanged": "workLogs",
  "message": " logged 30 min",
  "newValue": "30 min",
  "timestamp": {
    "$date": "2025-10-13T14:06:19.001Z"
  },
  "_class": "com.lm.project.project_management.pms.model.timeline.Timeline"
},
{
  "_id": {
    "$binary": {
      "base64": "1WAQ89uDCh99dwzdNSvouw==",
      "subType": "03"
    }
  },
  "business": {
    "_id": {
      "$binary": {
        "base64": "img60ibL7R4pstoZnVdjvQ==",
        "subType": "03"
      }
    },
    "name": "Simpo.ai"
  },
  "project": {
    "_id": {
      "$binary": {
        "base64": "gEhAby2IUhRLhfLyr3iclA==",
        "subType": "03"
      }
    },
    "name": "Simpo Tech"
  },
  "workItemId": {
    "$binary": {
      "base64": "10hrS1Rubkl9elp14R3Csg==",
      "subType": "03"
    }
  },
  "workItemTitle": "Front End Session",
  "type": "UPDATED",
  "user": {
    "_id": {
      "$binary": {
        "base64": "qWgg1ryqBx+oLnNj2numnw==",
        "subType": "03"
      }
    },
    "name": "Akhil"
  },
  "message": " updated the work item details.",
  "timestamp": {
    "$date": "2025-10-13T14:06:00.261Z"
  },
  "_class": "com.lm.project.project_management.pms.model.timeline.Timeline"
},
{
  "_id": {
    "$binary": {
      "base64": "BWEGUduDCh/NyAZvRYfouw==",
      "subType": "03"
    }
  },
  "business": {
    "_id": {
      "$binary": {
        "base64": "img60ibL7R4pstoZnVdjvQ==",
        "subType": "03"
      }
    },
    "name": "Simpo.ai"
  },
  "project": {
    "_id": {
      "$binary": {
        "base64": "gEhAby2IUhRLhfLyr3iclA==",
        "subType": "03"
      }
    },
    "name": "Simpo Tech"
  },
  "workItemId": {
    "$binary": {
      "base64": "10hrS1Rubkl9elp14R3Csg==",
      "subType": "03"
    }
  },
  "workItemTitle": "Front End Session",
  "type": "TIME_LOGGED",
  "user": {
    "_id": {
      "$binary": {
        "base64": "qWgg1ryqBx+oLnNj2numnw==",
        "subType": "03"
      }
    },
    "name": "Akhil"
  },
  "commentText": "Done !",
  "fieldChanged": "workLogs",
  "message": " logged 1 hr 30 min",
  "newValue": "1 hr 30 min",
  "timestamp": {
    "$date": "2025-10-13T14:05:43.270Z"
  },
  "_class": "com.lm.project.project_management.pms.model.timeline.Timeline"
},
{
  "_id": {
    "$binary": {
      "base64": "WGNmUNqDCh9E5+OGQcfouw==",
      "subType": "03"
    }
  },
  "business": {
    "_id": {
      "$binary": {
        "base64": "img60ibL7R4pstoZnVdjvQ==",
        "subType": "03"
      }
    },
    "name": "Simpo.ai"
  },
  "project": {
    "_id": {
      "$binary": {
        "base64": "gEhAby2IUhRLhfLyr3iclA==",
        "subType": "03"
      }
    },
    "name": "Simpo Tech"
  },
  "workItemId": {
    "$binary": {
      "base64": "2kuIsBsxJHxovXsLJXWjmw==",
      "subType": "03"
    }
  },
  "workItemTitle": "Editor Migration From Simpo Website Builder to Simpo Studio ",
  "type": "STATE_CHANGED",
  "user": {
    "_id": {
      "$binary": {
        "base64": "qWgg1ryqBx+oLnNj2numnw==",
        "subType": "03"
      }
    },
    "name": "Akhil"
  },
  "fieldChanged": "State",
  "message": " changed state from Backlog to Done.",
  "oldValue": "Backlog",
  "newValue": "Done",
  "timestamp": {
    "$date": "2025-10-13T14:05:16.361Z"
  },
  "_class": "com.lm.project.project_management.pms.model.timeline.Timeline"
},
{
  "_id": {
    "$binary": {
      "base64": "W20+GLmDCh9aAqgN+a/ouw==",
      "subType": "03"
    }
  },
  "business": {
    "_id": {
      "$binary": {
        "base64": "img60ibL7R4pstoZnVdjvQ==",
        "subType": "03"
      }
    },
    "name": "Simpo.ai"
  },
  "project": {
    "_id": {
      "$binary": {
        "base64": "gEhAby2IUhRLhfLyr3iclA==",
        "subType": "03"
      }
    },
    "name": "Simpo Tech"
  },
  "workItemId": {
    "$binary": {
      "base64": "bk+WzSCWATGH+957QQa7qw==",
      "subType": "03"
    }
  },
  "workItemTitle": "Worked on customer tickets for V M Muslunkar Jewellers – Change Customer IDs",
  "type": "STATE_CHANGED",
  "user": {
    "_id": {
      "$binary": {
        "base64": "B2hcg3zBBx+C2ChNqqk5uQ==",
        "subType": "03"
      }
    },
    "name": "Prasad lokireddy"
  },
  "fieldChanged": "State",
  "message": " changed state from In-Progress to Done.",
  "oldValue": "In-Progress",
  "newValue": "Done",
  "timestamp": {
    "$date": "2025-10-13T13:50:24.636Z"
  },
  "_class": "com.lm.project.project_management.pms.model.timeline.Timeline"
}]