{
  "_id": {
    "$binary": {
      "base64": "zE4VMRLAEaOYDcMZwn+Qqg==",
      "subType": "03"
    }
  },
  "project": {
    "_id": {
      "$binary": {
        "base64": "DE4aLoYUWpnD3YavQrjziQ==",
        "subType": "03"
      }
    },
    "name": "Helpdesk"
  },
  "displayBugNo": "HELPD-2",
  "status": "ACCEPTED",
  "createdBy": {
    "_id": {
      "$binary": {
        "base64": "f20oljII4h77Rw6nxB+Opw==",
        "subType": "03"
      }
    },
    "name": "prince monga"
  },
  "createdTimeStamp": {
    "$date": "2025-07-26T08:12:23.327Z"
  },
  "updatedTimeStamp": {
    "$date": "2025-07-26T08:12:23.327Z"
  },
  "title": "aldas",
  "description": "asdasd",
  "startDate": {
    "$date": "2025-06-30T18:30:00.000Z"
  },
  "endDate": {
    "$date": "2025-07-24T18:30:00.000Z"
  },
  "stateMaster": {
    "_id": {
      "$binary": {
        "base64": "n2SpwACfBh/0O6hav2dxgg==",
        "subType": "03"
      }
    },
    "name": "Started"
  },
  "state": {
    "_id": {
      "$binary": {
        "base64": "oGSpwACfBh8MKkkMWOtxgg==",
        "subType": "03"
      }
    },
    "name": "Started"
  },
  "business": {
    "_id": {
      "$binary": {
        "base64": "2WmoOacvBh8PLbeH1INshQ==",
        "subType": "03"
      }
    },
    "name": "Milan Jewellers"
  },
  "priority": "MEDIUM",
  "assignee": [
    {
      "_id": {
        "$binary": {
          "base64": "kW9ITdO1AR9aANvcYy2QuA==",
          "subType": "03"
        }
      },
      "name": "vivek"
    },
    {
      "_id": {
        "$binary": {
          "base64": "f20oljII4h77Rw6nxB+Opw==",
          "subType": "03"
        }
      },
      "name": "prince monga"
    }
  ],
  "cycle": {
    "_id": {
      "$binary": {
        "base64": "eU5OiG94aJsrDTuhRHpHqQ==",
        "subType": "03"
      }
    },
    "name": "testing"
  },
  "modules": {
    "_id": {
      "$binary": {
        "base64": "Ik9Um8XKURUwqLX7H5Pijg==",
        "subType": "03"
      }
    },
    "name": "testa"
  },
  "_class": "com.lm.project.project_management.pms.model.WorkItem"
}